.gitignore
flet_page_manager-0.2.7.dist-info/METADATA
flet_page_manager-0.2.7.dist-info/WHEEL
page_manager/__init__.py
page_manager/exception.py
page_manager/manager.py
page_manager/pages/__init__.py
page_manager/pages/base.py
page_manager/state.py
page_manager/utils.py
flet_page_manager-0.2.7.dist-info/RECORD
