Metadata-Version: 2.1
Name: flet-page-manager
Version: 0.2.7
Summary: A simple window manager for Flet that allows you to easily build multi-window applications.
Author-Email: Zhan Rongrui <2742392377@qq.com>
License: MIT
Project-URL: Homepage, https://github.com/zrr1999/flet-page-manager
Project-URL: Repository, https://github.com/zrr1999/flet-page-manager
Requires-Python: >=3.10
Requires-Dist: flet>=0.22.1
Requires-Dist: loguru>=0.7.2
Requires-Dist: pydantic>=2.0.0
